scrapy_selenium_middleware/__init__.py
scrapy_selenium_middleware/middleware.py
scrapy_selenium_middleware-0.0.5.dist-info/LICENSE.txt
scrapy_selenium_middleware-0.0.5.dist-info/METADATA
scrapy_selenium_middleware-0.0.5.dist-info/WHEEL
scrapy_selenium_middleware-0.0.5.dist-info/top_level.txt
scrapy_selenium_middleware-0.0.5.dist-info/RECORD
