Metadata-Version: 2.1
Name: scrapy-selenium-middleware
Version: 0.0.5
Summary: Scrapy middleware for downloading a page html source using selenium,
Home-page: https://github.com/Tal-Leibman/scrapy-selenium-middleware
Author: Tal Leibman
Author-email: leibman2@gmail.com
License: UNKNOWN
Keywords: scrapy,selenium,middleware,proxy,web scraping,render javascript,selenium-wire,headless browser
Platform: UNKNOWN
Requires-Dist: scrapy (==2.4.0)
Requires-Dist: selenium-wire (==2.1.1)
Requires-Dist: selenium (==3.141.0)
